softboxen/__init__.py
softboxen/cmd/__init__.py
softboxen/cmd/cli.py
tests/__init__.py
tests/__main__.py
tests/integration/__init__.py
tests/integration/__main__.py
tests/integration/test_samples.py
tests/unit/__init__.py
tests/unit/__main__.py
tests/unit/test_base.py
softboxen-0.0.0.dist-info/LICENSE.rst
softboxen-0.0.0.dist-info/METADATA
softboxen-0.0.0.dist-info/WHEEL
softboxen-0.0.0.dist-info/entry_points.txt
softboxen-0.0.0.dist-info/top_level.txt
softboxen-0.0.0.dist-info/zip-safe
softboxen-0.0.0.dist-info/RECORD
