Metadata-Version: 2.1
Name: softboxen
Version: 0.0.0
Summary: Network equipment simulator
Home-page: https://github.com/etingof/softboxen
Author: Ilya Etingof
Author-email: etingof@gmail.com
Maintainer: Ilya Etingof <etingof@gmail.com>
License: BSD
Platform: any
Classifier: Development Status :: 3 - Alpha
Classifier: Environment :: Console
Classifier: Intended Audience :: Developers
Classifier: Intended Audience :: Education
Classifier: Intended Audience :: Information Technology
Classifier: Intended Audience :: System Administrators
Classifier: Intended Audience :: Telecommunications Industry
Classifier: License :: OSI Approved :: BSD License
Classifier: Natural Language :: English
Classifier: Operating System :: OS Independent
Classifier: Programming Language :: Python :: 3
Classifier: Programming Language :: Python :: 3.6
Classifier: Programming Language :: Python :: 3.7
Classifier: Topic :: Communications
Classifier: Topic :: Software Development :: Libraries :: Python Modules
